s3go/__init__.py
s3go/s3go.py
s3go-0.1.dist-info/DESCRIPTION.rst
s3go-0.1.dist-info/METADATA
s3go-0.1.dist-info/RECORD
s3go-0.1.dist-info/WHEEL
s3go-0.1.dist-info/metadata.json
s3go-0.1.dist-info/top_level.txt
