Metadata-Version: 2.0
Name: s3go
Version: 0.1
Summary: upload local folder to s3 bucket
Home-page: https://github.com/flyfj/s3deploy
Author: Jie Feng
Author-email: jiefengdev@gmail.com
License: MIT
Platform: UNKNOWN
Requires-Dist: boto3
Requires-Dist: tqdm
